pyplurky/__init__.py
pyplurky/api.py
pyplurky/error.py
pyplurky/handler.py
pyplurky/job.py
pyplurky/karma.py
pyplurky/oauth2.py
pyplurky/plurk.py
pyplurky/profile.py
pyplurky/pyplurky.py
pyplurky/realtime.py
pyplurky/user.py
pyplurky/util.py
pyplurky-0.3.2.dist-info/LICENSE
pyplurky-0.3.2.dist-info/METADATA
pyplurky-0.3.2.dist-info/WHEEL
pyplurky-0.3.2.dist-info/top_level.txt
pyplurky-0.3.2.dist-info/RECORD
