Metadata-Version: 2.1
Name: pyplurky
Version: 0.3.2
Summary: A plurk-bot pack with plurk-api wrapper written in Python.
Home-page: https://github.com/Dephilia/PyPlurky
Author: Dephilia
Author-email: leedaniel682@gmail.com
License: UNKNOWN
Platform: UNKNOWN
Requires-Python: >=3.5
Requires-Dist: schedule
Requires-Dist: plurk-oauth
